Metadata-Version: 1.1
Name: randomEmailidGenerator
Version: 0.0.1
Summary: A very basic random email id generator
Home-page: UNKNOWN
Author: Pranay Bankar
Author-email: pranaybankar2890@gmail.com
License: MIT
Keywords: email generator
Platform: UNKNOWN
Classifier: Development Status :: 5 - Production/Stable
Classifier: Intended Audience :: Education
Classifier: Operating System :: Microsoft :: Windows :: Windows 10
Classifier: License :: OSI Approved :: MIT License
Classifier: Programming Language :: Python :: 3
